mousetail/__init__.py
mousetail/mcp/__init__.py
mousetail/mcp/server.py
mousetail/mcp/stdio_server.py
mousetail/mcp/tools.py
mousetail/server/__init__.py
mousetail/server/collection_manager.py
mousetail-0.1.3.dist-info/METADATA
mousetail-0.1.3.dist-info/WHEEL
mousetail-0.1.3.dist-info/entry_points.txt
mousetail-0.1.3.dist-info/licenses/LICENSE
mousetail-0.1.3.dist-info/RECORD
