Metadata-Version: 2.4
Name: mousetail
Version: 0.1.3
Summary: Standalone MCP server that enables LLMs like Claude to interact with Anki flashcard collections using Anki's Python library
Project-URL: Homepage, https://listfold.github.io/mousetail/
Project-URL: Repository, https://github.com/listfold/mousetail
Project-URL: Documentation, https://listfold.github.io/mousetail/
Project-URL: Issues, https://github.com/listfold/mousetail/issues
Author: Iain Maitland
License: MIT
License-File: LICENSE
Keywords: anki,claude,flashcards,llm,mcp,model-context-protocol,spaced-repetition
Requires-Python: >=3.10
Requires-Dist: anki>=25.9.2
Requires-Dist: mcp>=1.21.0
Provides-Extra: docs
Requires-Dist: furo>=2024.0.0; extra == 'docs'
Requires-Dist: sphinx-autodoc-typehints>=2.0.0; extra == 'docs'
Requires-Dist: sphinx>=7.0.0; extra == 'docs'
